MANIFEST.in
README.rst
setup.py
bin/exitnaver
exitnaver/__init__.py
exitnaver.egg-info/PKG-INFO
exitnaver.egg-info/SOURCES.txt
exitnaver.egg-info/dependency_links.txt
exitnaver.egg-info/pbr.json
exitnaver.egg-info/requires.txt
exitnaver.egg-info/top_level.txt