Metadata-Version: 1.1
Name: exitnaver
Version: 0.2.1
Summary: Exports your Naver blog in Markdown format.
Home-page: https://github.com/limeburst/exitnaver
Author: Jihyeok Seo
Author-email: me@limeburst.net
License: GPL
Platform: UNKNOWN
Classifier: Development Status :: 4 - Beta
Classifier: Environment :: Console
Classifier: License :: OSI Approved :: GNU General Public License (GPL)
Classifier: Programming Language :: Python
Classifier: Topic :: Internet :: WWW/HTTP
Classifier: Topic :: Software Development :: Libraries :: Python Modules
